cythonizer/__init__.py
cythonizer/apps.py
cythonizer/build_tools/__init__.py
cythonizer/build_tools/build_command.py
cythonizer/build_tools/config.py
cythonizer/build_tools/cython_compiler.py
cythonizer/build_tools/file_operations.py
cythonizer/build_tools/logging_setup.py
cythonizer/build_tools/settings.yaml
cythonizer/build_tools/spinner.py
cythonizer/management/commands/cythoniz.py
django_cythonizer-0.0.12.dist-info/LICENSE
django_cythonizer-0.0.12.dist-info/METADATA
django_cythonizer-0.0.12.dist-info/WHEEL
django_cythonizer-0.0.12.dist-info/entry_points.txt
django_cythonizer-0.0.12.dist-info/top_level.txt
django_cythonizer-0.0.12.dist-info/RECORD
