Metadata-Version: 2.1
Name: django-cythonizer
Version: 0.0.12
Summary: A Django package for Cythonizing Django projects
Home-page: https://github.com/salah-alhajj/django-cythonizer
Author: Salah Aldain Alhajj
Author-email: Salah Aldain Alhajj <contact@salahaldain.com>
License: MIT License with Usage Disclosure
Project-URL: Homepage, https://github.com/salah-alhajj/django-cythonizer
Project-URL: Repository, https://github.com/salah-alhajj/django-cythonizer.git
Project-URL: Bug Tracker, https://github.com/salah-alhajj/django-cythonizer/issues
Keywords: django,cython,optimization,performance,compilation
Classifier: Development Status :: 3 - Alpha
Classifier: Intended Audience :: Developers
Classifier: License :: OSI Approved :: MIT License
Classifier: Programming Language :: Python :: 3
Classifier: Programming Language :: Python :: 3.8
Classifier: Programming Language :: Python :: 3.9
Classifier: Programming Language :: Python :: 3.10
Classifier: Programming Language :: Python :: 3.11
Classifier: Framework :: Django
Classifier: Framework :: Django :: 4.2
Requires-Python: >=3.6
License-File: LICENSE
Requires-Dist: Django <5.0,>=4.2
Requires-Dist: djangorestframework
Requires-Dist: Cython ==3.0.10
Requires-Dist: PyYAML >=6.0.1
Provides-Extra: dev
Requires-Dist: pytest >=6.0 ; extra == 'dev'
Requires-Dist: pytest-django ; extra == 'dev'
Requires-Dist: black ; extra == 'dev'
Requires-Dist: isort ; extra == 'dev'
Requires-Dist: flake8 ; extra == 'dev'
Requires-Dist: mypy ; extra == 'dev'
